{
  "app": "com.nintendo.zama",
  "duration": "343ms",
  "headers": {
    "X-Unity-Version": "2018.4.21f1",
    "User-Agent": "Dalvik/2.1.0 (Linux; U; Android 10; Mi A1 Build/QD4A.200905.003)",
    "Host": "game-lgmatcha.line-scdn.net",
    "Connection": "Keep-Alive",
    "Accept-Encoding": "gzip"
  },
  "method": "GET",
  "protocol": "HTTP/1.1",
  "remoteIp": "54.230.96.51",
  "remotePort": 443,
  "sessionId": "6931ce5b-2a20-4865-8830-09eea70d13a2",
  "time": "2021-10-13 21:19:05",
  "url": "https://game-lgmatcha.line-scdn.net/r/real/AssetBundles/Android/829/character.drfirepeach"
}