{
  "app": "com.nintendo.zama",
  "code": 200,
  "duration": "335ms",
  "headers": {
    "Content-Type": "text/cache-manifest; charset\u003dutf-8",
    "Content-Length": "974",
    "Connection": "keep-alive",
    "Server": "VOS",
    "Accept-Ranges": "bytes",
    "Last-Modified": "Thu, 26 Aug 2021 05:57:33 GMT",
    "x-amz-version-id": "M1OIrnMH4k3CpwMg7Zl1nDByCjH.3I.",
    "x-rgw-object-type": "Normal",
    "x-amz-meta-mtime": "1629876273",
    "Strict-Transport-Security": "max-age\u003d15768000",
    "Date": "Wed, 13 Oct 2021 16:19:42 GMT",
    "Cache-Control": "public,max-age\u003d300",
    "ETag": "\"81851d891572b6d438c4ecf9bfb5285b\"",
    "X-Cache": "RefreshHit from cloudfront",
    "Via": "1.1 3529bf84e9522012233c3dd2a59fdfe9.cloudfront.net (CloudFront)",
    "X-Amz-Cf-Pop": "ARN1-C1",
    "X-Amz-Cf-Id": "hcnr_Qv-202Su4kSQW-ZFuEmLHEt6El7MHtpdcBF_0aobndc1ISwPw\u003d\u003d"
  },
  "message": "OK",
  "protocol": "HTTP/1.1",
  "remoteIp": "54.230.96.51",
  "remotePort": 443,
  "sessionId": "428003e6-eb24-48ed-80c5-9eff81342ff3",
  "time": "2021-10-13 21:19:42"
}