{
  "app": "com.nintendo.zama",
  "code": 200,
  "duration": "352ms",
  "headers": {
    "Content-Type": "application/octet-stream",
    "Content-Length": "350294",
    "Connection": "keep-alive",
    "Server": "VOS",
    "Accept-Ranges": "bytes",
    "Last-Modified": "Thu, 26 Aug 2021 05:57:33 GMT",
    "x-amz-version-id": "lDg8djEwiXFdhGfSDLuVOpTuolQObeF",
    "x-rgw-object-type": "Normal",
    "x-amz-meta-mtime": "1629876273",
    "Strict-Transport-Security": "max-age\u003d15768000",
    "Date": "Wed, 13 Oct 2021 16:19:42 GMT",
    "Cache-Control": "public,max-age\u003d300",
    "ETag": "\"b394126e272942b4b6021e8641728478\"",
    "X-Cache": "RefreshHit from cloudfront",
    "Via": "1.1 ffa40c4091d11859ad05cf9748508c58.cloudfront.net (CloudFront)",
    "X-Amz-Cf-Pop": "ARN1-C1",
    "X-Amz-Cf-Id": "LmQ-l2asbd6OFVw6ZuSmd3tszfN0DpUPh01Us2dLXPj3rR8nEg9ZBQ\u003d\u003d"
  },
  "message": "OK",
  "protocol": "HTTP/1.1",
  "remoteIp": "54.230.96.51",
  "remotePort": 443,
  "sessionId": "3c57ed41-b9b6-40a8-81f5-4867b9220fc0",
  "time": "2021-10-13 21:19:42"
}