{
  "app": "com.nintendo.zama",
  "code": 200,
  "duration": "354ms",
  "headers": {
    "Content-Type": "text/cache-manifest; charset\u003dutf-8",
    "Content-Length": "2429",
    "Connection": "keep-alive",
    "Server": "VOS",
    "Accept-Ranges": "bytes",
    "Last-Modified": "Thu, 26 Aug 2021 05:57:33 GMT",
    "x-amz-version-id": "Baz384Znc2mdwKz6jVjTyO40J3SztCO",
    "x-rgw-object-type": "Normal",
    "x-amz-meta-mtime": "1629876273",
    "Strict-Transport-Security": "max-age\u003d15768000",
    "Date": "Wed, 13 Oct 2021 16:19:35 GMT",
    "Cache-Control": "public,max-age\u003d300",
    "ETag": "\"1f8718280aadb2e4a8f78c25aa1b5a61\"",
    "X-Cache": "RefreshHit from cloudfront",
    "Via": "1.1 ffa40c4091d11859ad05cf9748508c58.cloudfront.net (CloudFront)",
    "X-Amz-Cf-Pop": "ARN1-C1",
    "X-Amz-Cf-Id": "CMFhsb6zzEEJM-Iq35PAd6W4zzedfldTG1qMGzlPx9oRyHjZ2kH4Fw\u003d\u003d"
  },
  "message": "OK",
  "protocol": "HTTP/1.1",
  "remoteIp": "54.230.96.51",
  "remotePort": 443,
  "sessionId": "5631b123-3aab-4e48-a0c9-9faa29484b85",
  "time": "2021-10-13 21:19:36"
}